geolambert/__init__.py
geolambert/clambert.so
geolambert/geolambert.py
geolambert-0.1.1.dist-info/DESCRIPTION.rst
geolambert-0.1.1.dist-info/METADATA
geolambert-0.1.1.dist-info/RECORD
geolambert-0.1.1.dist-info/WHEEL
geolambert-0.1.1.dist-info/metadata.json
geolambert-0.1.1.dist-info/top_level.txt
